[
    {
        "id": "302",
        "filter_size": "24x24x2",
        "filter_type": "Paper",
        "filter_count": "252",
        "par": "720",
        "storage": "",
        "notes": "",
        "date_updated": "2023-12-04",
        "pn": ""
    },
    {
        "id": "303",
        "filter_size": "29x29x2",
        "filter_type": "Paper",
        "filter_count": "31",
        "par": "24",
        "storage": "",
        "notes": "Ah-21C rm",
        "date_updated": "2023-12-16",
        "pn": ""
    },
    {
        "id": "307",
        "filter_size": "20x20x2",
        "filter_type": "Paper",
        "filter_count": 5,
        "par": "140",
        "storage": "",
        "notes": "none",
        "date_updated": "2023-12-04",
        "pn": ""
    },
    {
        "id": "308",
        "filter_size": "18x24x2",
        "filter_type": "Paper",
        "filter_count": 73,
        "par": "12",
        "storage": null,
        "notes": "none",
        "date_updated": "2023-10-27",
        "pn": null
    },
    {
        "id": "309",
        "filter_size": "18x20x2",
        "filter_type": "Paper",
        "filter_count": "58",
        "par": "12",
        "storage": null,
        "notes": "",
        "date_updated": "2023-10-27",
        "pn": null
    },
    {
        "id": "310",
        "filter_size": "16x32x2",
        "filter_type": "Paper",
        "filter_count": "120",
        "par": "24",
        "storage": ",mezz filter rm",
        "notes": "AH-21C Equipment Rm",
        "date_updated": "2023-12-04",
        "pn": ""
    },
    {
        "id": "312",
        "filter_size": "25x25x2",
        "filter_type": "Paper",
        "filter_count": 268,
        "par": "12",
        "storage": "",
        "notes": "S. Mezz filter room Ah-3",
        "date_updated": "2023-10-31",
        "pn": null
    },
    {
        "id": "315",
        "filter_size": "16x25x2",
        "filter_type": "Paper",
        "filter_count": 165,
        "par": "140",
        "storage": "",
        "notes": "none",
        "date_updated": "2023-10-26",
        "pn": ""
    },
    
    {
        "id": "316",
        "filter_size": "10x28x1",
        "filter_type": "Paper",
        "filter_count": 59,
        "par": "12",
        "storage": ",mezz filter rm",
        "notes": "",
        "date_updated": "2023-12-04",
        "pn": ""
    },
    {
        "id": "317",
        "filter_size": "14x14x1",
        "filter_type": "Paper",
        "filter_count": "120",
        "par": "120",
        "storage": "",
        "notes": "no units use this size",
        "date_updated": "2023-11-04",
        "pn": null
    },
    {
        "id": "318",
        "filter_size": "14x20x1",
        "filter_type": "Paper",
        "filter_count": 68,
        "par": "12",
        "storage": null,
        "notes": "none",
        "date_updated": "2023-10-27",
        "pn": null
    },
    {
        "id": "319",
        "filter_size": "14x35x1",
        "filter_type": "Paper",
        "filter_count": 76,
        "par": "12",
        "storage": null,
        "notes": "none",
        "date_updated": "2023-10-27",
        "pn": null
    },
     {
        "id": "320",
        "filter_size": "14x34x1",
        "filter_type": "Paper",
        "filter_count": "72",
        "par": "12",
        "storage": null,
        "notes": "none",
        "date_updated": "2023-10-26",
        "pn": null
    },
    {
        "id": "321",
        "filter_size": "17x17x1",
        "filter_type": "Paper",
        "filter_count": 144,
        "par": "12",
        "storage": "mezz filter rm,conv filter rm",
        "notes": "none",
        "date_updated": "2023-11-12",
        "pn": ""
    },
    {
        "id": "323",
        "filter_size": "16x20x1",
        "filter_type": "Paper",
        "filter_count": "78",
        "par": "24",
        "storage": "",
        "notes": "none",
        "date_updated": "2023-11-12",
        "pn": ""
    },
    {
        "id": "324",
        "filter_size": "20x20x1",
        "filter_type": "Paper",
        "filter_count": 208,
        "par": "60",
        "storage": ",mezz filter rm",
        "notes": "none",
        "date_updated": "2023-11-24",
        "pn": ""
    },
    {
        "id": "325",
        "filter_size": "20x25x1",
        "filter_type": "Paper",
        "filter_count": "67",
        "par": "12",
        "storage": "",
        "notes": "none",
        "date_updated": "2023-11-14",
        "pn": ""
    },
    {
        "id": "326",
        "filter_size": "20x30x1",
        "filter_type": "Paper",
        "filter_count": "234",
        "par": "12",
        "storage": ",conv filter rm",
        "notes": "none",
        "date_updated": "2024-01-16",
        "pn": ""
    },
    {
        "id": "327",
        "filter_size": "12x24x2",
        "filter_type": "Paper",
        "filter_count": 156,
        "par": "72",
        "storage": "",
        "notes": "South Mezz Filter Rm Ah-3",
        "date_updated": "2023-12-04",
        "pn": ""
    },
    {
        "id": "328",
        "filter_size": "17x22x1",
        "filter_type": "Paper",
        "filter_count": 132,
        "par": "12",
        "storage": "conv filter rm",
        "notes": "",
        "date_updated": "2023-11-12",
        "pn": ""
    },
    {
        "id": "329",
        "filter_size": "16x24x2",
        "filter_type": "Paper",
        "filter_count": 149,
        "par": "12",
        "storage": null,
        "notes": "none",
        "date_updated": "2023-10-26",
        "pn": null
    },
   {
        "id": "330",
        "filter_size": "16x20x2",
        "filter_type": "Paper",
        "filter_count": 72,
        "par": "60",
        "storage": null,
        "notes": "none",
        "date_updated": "2023-10-26",
        "pn": null
    },
    {
        "id": "331",
        "filter_size": "17x40x1",
        "filter_type": "Paper",
        "filter_count": 108,
        "par": "24",
        "storage": "",
        "notes": "none",
        "date_updated": "2023-10-31",
        "pn": null
    },
    {
        "id": "333",
        "filter_size": "12x25x1",
        "filter_type": "Paper",
        "filter_count": "96",
        "par": "144",
        "storage": ",conv filter rm",
        "notes": " no units use this size",
        "date_updated": "2023-12-04",
        "pn": ""
    },
    {
        "id": "334",
        "filter_size": "24x24x12",
        "filter_type": "Extended 12 inch",
        "filter_count": "288",
        "par": "520",
        "storage": ",mezz filter rm",
        "notes": "This size is being discontinued Located in the Parking Garage",
        "date_updated": "2023-12-04",
        "pn": ""
    },
    {
        "id": "335",
        "filter_size": "10x22x1",
        "filter_type": "Paper",
        "filter_count": "12",
        "par": "0",
        "storage": "",
        "notes": "",
        "date_updated": "2023-10-27",
        "pn": ""
    },
    {
        "id": "336",
        "filter_size": "16x30x2",
        "filter_type": "Paper",
        "filter_count": "80",
        "par": "60",
        "storage": null,
        "notes": "No units use this size",
        "date_updated": "2023-10-26",
        "pn": null
    },
    {
        "id": "337",
        "filter_size": "10x20x2",
        "filter_type": "Paper",
        "filter_count": "12",
        "par": "12",
        "storage": ",mezz filter rm",
        "notes": "none",
        "date_updated": "2023-12-04",
        "pn": ""
    },
    {
        "id": "339",
        "filter_size": "20x24x12",
        "filter_type": "Extended 12 inch",
        "filter_count": "180",
        "par": "24",
        "storage": null,
        "notes": "none",
        "date_updated": "2023-07-04",
        "pn": null
    },
    {
        "id": "341",
        "filter_size": "17x34x1",
        "filter_type": "Paper",
        "filter_count": 222,
        "par": "12",
        "storage": "mezz filter rm,conv filter rm",
        "notes": "none",
        "date_updated": "2023-11-12",
        "pn": ""
    },
    {
        "id": "342",
        "filter_size": "15x32x2",
        "filter_type": "Paper",
        "filter_count": "12",
        "par": "12",
        "storage": null,
        "notes": "none",
        "date_updated": "2022-01-16",
        "pn": null
    },
    {
        "id": "343",
        "filter_size": "20x24x2",
        "filter_type": "Extended 2 inch",
        "filter_count": "48",
        "par": "24",
        "storage": "",
        "notes": "none",
        "date_updated": "2023-10-27",
        "pn": ""
    },
    {
        "id": "344",
        "filter_size": "20x20x2",
        "filter_type": "Extended 2 inch",
        "filter_count": 82,
        "par": "72",
        "storage": null,
        "notes": "Mezz filter room",
        "date_updated": "2023-10-27",
        "pn": null
    },
    {
        "id": "345",
        "filter_size": "12x24x12",
        "filter_type": "Paper",
        "filter_count": 46,
        "par": "12",
        "storage": null,
        "notes": "none",
        "date_updated": "2022-01-16",
        "pn": null
    },
    {
        "id": "346",
        "filter_size": "10x20x1",
        "filter_type": "Paper",
        "filter_count": "22",
        "par": "24",
        "storage": ",mezz filter rm",
        "notes": "none",
        "date_updated": "2023-11-24",
        "pn": ""
    },
    {
        "id": "347",
        "filter_size": "10x24x1",
        "filter_type": "Paper",
        "filter_count": "12",
        "par": "12",
        "storage": null,
        "notes": "no units use this size",
        "date_updated": "2023-10-26",
        "pn": null
    },
    {
        "id": "348",
        "filter_size": "12x17x1",
        "filter_type": "Paper",
        "filter_count": "24",
        "par": "12",
        "storage": null,
        "notes": "no units take this size",
        "date_updated": "2023-10-27",
        "pn": null
    },
    {
        "id": "349",
        "filter_size": "12x20x1",
        "filter_type": "Paper",
        "filter_count": "48",
        "par": "12",
        "storage": null,
        "notes": "none",
        "date_updated": "2023-10-27",
        "pn": null
    },
    {
        "id": "351",
        "filter_size": "17x52x1",
        "filter_type": "Paper",
        "filter_count": 94,
        "par": "12",
        "storage": "",
        "notes": "none",
        "date_updated": "2023-10-31",
        "pn": null
    },
    {
        "id": "352",
        "filter_size": "17x54x1",
        "filter_type": "Paper",
        "filter_count": "34",
        "par": "12",
        "storage": null,
        "notes": "none",
        "date_updated": "2023-10-26",
        "pn": null
    },
    {
        "id": "353",
        "filter_size": "16x30x1",
        "filter_type": "Paper",
        "filter_count": "593",
        "par": "20",
        "storage": "mezz filter rm,conv filter rm",
        "notes": "Most at mec filter room",
        "date_updated": "2023-11-12",
        "pn": ""
    },
    {
        "id": "387",
        "filter_size": "20x24x2",
        "filter_type": "Paper",
        "filter_count": 93,
        "par": "144",
        "storage": "",
        "notes": "S. Mez filter rm Ah-3",
        "date_updated": "2023-11-24",
        "pn": ""
    },
    {
        "id": "355",
        "filter_size": "17x46x1",
        "filter_type": "Paper",
        "filter_count": 103,
        "par": "0",
        "storage": "mezz filter rm,conv filter rm",
        "notes": "",
        "date_updated": "2023-11-12",
        "pn": ""
    },
    {
        "id": "357",
        "filter_size": "17x28x1",
        "filter_type": "Paper",
        "filter_count": 93,
        "par": "12",
        "storage": "",
        "notes": "none",
        "date_updated": "2023-10-31",
        "pn": null
    },
    {
        "id": "358",
        "filter_size": "17x26x1",
        "filter_type": "Paper",
        "filter_count": "302",
        "par": "12",
        "storage": "mezz filter rm,conv filter rm",
        "notes": "",
        "date_updated": "2023-11-12",
        "pn": ""
    },
    {
        "id": "359",
        "filter_size": "17x23x1",
        "filter_type": "Paper",
        "filter_count": "280",
        "par": "35",
        "storage": "mezz filter rm,conv filter rm",
        "notes": "no units take this size",
        "date_updated": "2023-11-12",
        "pn": ""
    },
    {
        "id": "361",
        "filter_size": "17x18x1",
        "filter_type": "Paper",
        "filter_count": "24",
        "par": "24",
        "storage": null,
        "notes": "no units use this size",
        "date_updated": "2023-10-26",
        "pn": null
    },
    {
        "id": "362",
        "filter_size": "16x25x1",
        "filter_type": "Paper",
        "filter_count": 627,
        "par": "24",
        "storage": "mezz filter rm,conv filter rm",
        "notes": "none",
        "date_updated": "2023-11-12",
        "pn": ""
    },
    {
        "id": "364",
        "filter_size": "10x16x1",
        "filter_type": "Paper",
        "filter_count": 70,
        "par": "12",
        "storage": "mezz filter rm,conv filter rm",
        "notes": "none",
        "date_updated": "2023-11-12",
        "pn": ""
    },
    {
        "id": "365",
        "filter_size": "20x20x12",
        "filter_type": "Extended 12 inch",
        "filter_count": "47",
        "par": "40",
        "storage": null,
        "notes": "none",
        "date_updated": "2023-07-04",
        "pn": null
    },
    {
        "id": "366",
        "filter_size": "22x29x2",
        "filter_type": "Paper",
        "filter_count": 102,
        "par": "36",
        "storage": null,
        "notes": "Inside Ah-21c rm",
        "date_updated": "2023-10-30",
        "pn": null
    },
    {
        "id": "367",
        "filter_size": "15x30x2",
        "filter_type": "Paper",
        "filter_count": "84",
        "par": "84",
        "storage": null,
        "notes": "no units use this size",
        "date_updated": "2023-10-26",
        "pn": null
    },
    {
        "id": "369",
        "filter_size": "24x24x2",
        "filter_type": "Extended 2 inch",
        "filter_count": "16",
        "par": "108",
        "storage": null,
        "notes": "In 21c AH rm",
        "date_updated": "2023-10-30",
        "pn": null
    },
    {
        "id": "375",
        "filter_size": "12x24x2",
        "filter_type": "Extended 2 inch",
        "filter_count": "-1",
        "par": "48",
        "storage": "",
        "notes": "",
        "date_updated": "2023-11-28",
        "pn": ""
    },
    {
        "id": "376",
        "filter_size": "16x25x2",
        "filter_type": "Extended 2 inch",
        "filter_count": "138",
        "par": "72",
        "storage": "",
        "notes": "",
        "date_updated": "2023-12-05",
        "pn": ""
    },
    {
        "id": "377",
        "filter_size": "20x25x2",
        "filter_type": "Paper",
        "filter_count": 455,
        "par": "240",
        "storage": "",
        "notes": "",
        "date_updated": "2023-12-04",
        "pn": ""
    },
    {
        "id": "378",
        "filter_size": "16x16x2",
        "filter_type": "Paper",
        "filter_count": 8,
        "par": "48",
        "storage": ",mezz filter rm",
        "notes": "",
        "date_updated": "2023-12-04",
        "pn": ""
    },
    {
        "id": "383",
        "filter_size": "16x20x2",
        "filter_type": "Extended 2 inch",
        "filter_count": 114,
        "par": "100",
        "storage": ",mezz filter rm",
        "notes": "",
        "date_updated": "2023-12-04",
        "pn": ""
    },
    {
        "id": "384",
        "filter_size": "12x24x1",
        "filter_type": "Paper",
        "filter_count": 129,
        "par": "12",
        "storage": "conv filter rm",
        "notes": "",
        "date_updated": "2023-11-12",
        "pn": ""
    },
    {
        "id": "388",
        "filter_size": "16x20x2",
        "filter_type": "Extended 12 inch",
        "filter_count": "80",
        "par": "100",
        "storage": null,
        "notes": "",
        "date_updated": "2023-08-15",
        "pn": null
    },
    {
        "id": "389",
        "filter_size": "17x18x1",
        "filter_type": "Paper",
        "filter_count": "24",
        "par": "0",
        "storage": null,
        "notes": "No units use this size",
        "date_updated": "2023-10-31",
        "pn": null
    },
    {
        "id": "391",
        "filter_size": "17x36x1",
        "filter_type": "Paper",
        "filter_count": "36",
        "par": "0",
        "storage": "conv filter rm",
        "notes": "mec filter rm",
        "date_updated": "2023-11-12",
        "pn": ""
    }
]